KeyExtractor/__init__.py
KeyExtractor/core.py
KeyExtractor/utils/__init__.py
KeyExtractor/utils/evaluation.py
KeyExtractor/utils/struct.py
KeyExtractor/utils/tokenization.py
KeyExtractor/utils/utility.py
KeyExtractor/utils/stopwords/__init__.py
KeyExtractor/utils/stopwords/zh/__init__.py
KeyExtractor/utils/stopwords/zh/baidu.py
KeyExtractor/utils/stopwords/zh/hit.py
KeyExtractor/utils/stopwords/zh/scu.py
KeyExtractor/utils/stopwords/zh/zhcn.py
KeyExtractor/utils/stopwords/zh/zhtw.py
KeyExtractor-0.1.2a1.dev1.dist-info/LICENSE
KeyExtractor-0.1.2a1.dev1.dist-info/METADATA
KeyExtractor-0.1.2a1.dev1.dist-info/WHEEL
KeyExtractor-0.1.2a1.dev1.dist-info/top_level.txt
KeyExtractor-0.1.2a1.dev1.dist-info/RECORD
