Metadata-Version: 2.1
Name: KeyExtractor
Version: 0.1.2a1.dev1
Summary: KeyExtractor performs keyword extraction for chinese documents with state-of-the-art transformer models.
Home-page: https://github.com/allenyummy/KeyExtractor.git
Author: Yu-Lun Chiang
Author-email: chiangyulun0914@gmail.com
License: UNKNOWN
Download-URL: https://github.com/allenyummy/KeyExtractor/archive/refs/tags/0.1.2a1.dev1.tar.gz
Platform: UNKNOWN
Classifier: Development Status :: 2 - Pre-Alpha
Classifier: Intended Audience :: Science/Research
Classifier: Intended Audience :: Developers
Classifier: Topic :: Software Development :: Build Tools
Classifier: Topic :: Scientific/Engineering :: Artificial Intelligence
Classifier: License :: OSI Approved :: MIT License
Classifier: Operating System :: Microsoft :: Windows
Classifier: Operating System :: Unix
Classifier: Operating System :: MacOS
Classifier: Programming Language :: Python :: 3.7
Classifier: Programming Language :: Python :: 3.8
Requires-Python: >=3.6
Requires-Dist: torch (==1.7.1)
Requires-Dist: flair (==0.8.0post1)
Requires-Dist: transformers (==4.5.0)
Requires-Dist: ckip-transformers (==0.2.3)
Provides-Extra: spa
Requires-Dist: spacy (==3.0.6) ; extra == 'spa'
Requires-Dist: spacy-transformers (==1.0.2) ; extra == 'spa'
Provides-Extra: test
Requires-Dist: pytest (==6.2.3) ; extra == 'test'
Requires-Dist: pytest-mock (==3.5.1) ; extra == 'test'
Requires-Dist: pytest-cov (==2.11.1) ; extra == 'test'
